opentelemetry/exporter/datadog/__init__.py
opentelemetry/exporter/datadog/constants.py
opentelemetry/exporter/datadog/exporter.py
opentelemetry/exporter/datadog/propagator.py
opentelemetry/exporter/datadog/spanprocessor.py
opentelemetry/exporter/datadog/version.py
opentelemetry_exporter_datadog-0.30b0.dist-info/METADATA
opentelemetry_exporter_datadog-0.30b0.dist-info/WHEEL
opentelemetry_exporter_datadog-0.30b0.dist-info/top_level.txt
opentelemetry_exporter_datadog-0.30b0.dist-info/RECORD
