Metadata-Version: 2.1
Name: opentelemetry-exporter-datadog
Version: 0.30b0
Summary: Datadog Span Exporter for OpenTelemetry
Home-page: https://github.com/open-telemetry/opentelemetry-python-contrib/exporter/opentelemetry-exporter-datadog
Author: OpenTelemetry Authors
Author-email: cncf-opentelemetry-contributors@lists.cncf.io
License: Apache-2.0
Platform: any
Classifier: Development Status :: 4 - Beta
Classifier: Intended Audience :: Developers
Classifier: License :: OSI Approved :: Apache Software License
Classifier: Programming Language :: Python
Classifier: Programming Language :: Python :: 3
Classifier: Programming Language :: Python :: 3.6
Classifier: Programming Language :: Python :: 3.7
Classifier: Programming Language :: Python :: 3.8
Classifier: Programming Language :: Python :: 3.9
Classifier: Programming Language :: Python :: 3.10
Requires-Python: >=3.6
Requires-Dist: ddtrace (<0.47.0,>=0.34.0)
Requires-Dist: opentelemetry-api (~=1.3)
Requires-Dist: opentelemetry-sdk (~=1.3)
Requires-Dist: opentelemetry-semantic-conventions (==0.30b0)
Provides-Extra: test
